gpt_developer_tools.py
src/__init__.py
src/__main__.py
src/requester.py
src/utils.py
tests/__init__.py
tests/test_cli.py
tests/test_model.py
gpt_developer_tools-0.0.1.dist-info/LICENSE
gpt_developer_tools-0.0.1.dist-info/METADATA
gpt_developer_tools-0.0.1.dist-info/WHEEL
gpt_developer_tools-0.0.1.dist-info/entry_points.txt
gpt_developer_tools-0.0.1.dist-info/top_level.txt
gpt_developer_tools-0.0.1.dist-info/RECORD
