Metadata-Version: 2.1
Name: gpt-developer-tools
Version: 0.0.1
Summary: A CLI tool that could debug, explain and create scripts using ChatGPT
Home-page: https://github.com/bovem/gpt-developer-tools
Author: Avnish Pal
Author-email: avnishnish07@gmail.com
License: MIT
Classifier: Programming Language :: Python :: 3.8
Classifier: Operating System :: OS Independent
Requires-Python: >=3.7
License-File: LICENSE
Requires-Dist: click (>=7.1.2)
Requires-Dist: openai (>=0.26.4)
